{"timestamp": 328188, "payload": [19, -21, 15, 30, 10, 7, 23, 18, 14, 16, 25, 10, 13, 27, 5], "label": 2}
{"timestamp": 328189, "payload": [20, -21, 14, 30, 11, 7, 23, 18, 13, 16, 26, 10, 12, 28, 7], "label": 2}
{"timestamp": 328196, "payload": [20, -22, 13, 30, 11, 7, 23, 19, 14, 16, 26, 10, 12, 28, 8], "label": 2}
{"timestamp": 328204, "payload": [21, -23, 12, 30, 12, 7, 23, 19, 14, 16, 27, 10, 13, 28, 9], "label": 2}
{"timestamp": 328204, "payload": [22, -23, 12, 30, 12, 7, 23, 19, 13, 16, 27, 10, 13, 29, 9], "label": 2}
{"timestamp": 328212, "payload": [22, -24, 11, 30, 13, 8, 23, 20, 14, 16, 27, 10, 13, 29, 9], "label": 2}
{"timestamp": 328212, "payload": [22, -23, 10, 30, 14, 8, 23, 21, 13, 15, 28, 11, 13, 29, 10], "label": 2}
{"timestamp": 328236, "payload": [21, -22, 11, 31, 14, 7, 23, 22, 14, 15, 29, 10, 13, 31, 10], "label": 2}
{"timestamp": 328244, "payload": [21, -22, 12, 31, 15, 7, 23, 22, 13, 15, 29, 10, 13, 31, 10], "label": 2}
{"timestamp": 328244, "payload": [20, -22, 13, 31, 14, 7, 23, 22, 13, 16, 29, 10, 13, 31, 10], "label": 2}
{"timestamp": 328252, "payload": [20, -22, 13, 30, 14, 7, 23, 22, 13, 15, 29, 10, 13, 31, 9], "label": 2}
{"timestamp": 328252, "payload": [20, -23, 14, 30, 14, 8, 23, 22, 13, 16, 29, 10, 13, 30, 8], "label": 2}
{"timestamp": 328260, "payload": [19, -23, 14, 29, 14, 9, 23, 21, 14, 16, 28, 9, 13, 30, 8], "label": 2}
{"timestamp": 328268, "payload": [18, -24, 15, 30, 14, 9, 23, 21, 14, 16, 28, 9, 13, 30, 7], "label": 2}
{"timestamp": 328268, "payload": [18, -25, 15, 30, 13, 9, 23, 21, 14, 16, 28, 9, 13, 30, 6], "label": 2}
{"timestamp": 328276, "payload": [17, -25, 16, 30, 13, 10, 22, 21, 14, 16, 28, 10, 13, 30, 6], "label": 2}
{"timestamp": 328284, "payload": [17, -25, 16, 30, 14, 11, 22, 22, 14, 16, 29, 9, 13, 30, 6], "label": 2}
{"timestamp": 328284, "payload": [16, -26, 17, 30, 14, 11, 22, 22, 14, 16, 29, 10, 13, 30, 6], "label": 2}
{"timestamp": 328292, "payload": [16, -26, 17, 29, 14, 11, 22, 22, 14, 16, 29, 9, 14, 31, 6], "label": 2}
{"timestamp": 328293, "payload": [16, -26, 17, 30, 14, 11, 23, 22, 15, 16, 29, 9, 13, 31, 6], "label": 2}
{"timestamp": 328300, "payload": [15, -26, 17, 29, 14, 11, 22, 22, 14, 16, 29, 9, 13, 31, 6], "label": 2}
{"timestamp": 328308, "payload": [15, -26, 17, 30, 14, 11, 23, 22, 14, 16, 29, 9, 13, 30, 6], "label": 2}
{"timestamp": 328309, "payload": [15, -27, 17, 29, 14, 11, 23, 22, 14, 16, 29, 9, 13, 31, 6], "label": 2}
{"timestamp": 328316, "payload": [16, -27, 18, 30, 14, 11, 22, 22, 15, 16, 29, 9, 13, 31, 6], "label": 2}
{"timestamp": 328324, "payload": [16, -27, 17, 30, 14, 11, 23, 22, 14, 16, 29, 9, 13, 30, 6], "label": 2}
{"timestamp": 328325, "payload": [16, -27, 17, 30, 14, 12, 22, 22, 15, 16, 28, 9, 13, 30, 6], "label": 2}
{"timestamp": 328332, "payload": [16, -27, 17, 30, 13, 11, 22, 21, 14, 16, 28, 9, 13, 30, 6], "label": 2}
{"timestamp": 328332, "payload": [16, -27, 16, 30, 13, 11, 22, 21, 14, 16, 28, 10, 13, 30, 7], "label": 2}
{"timestamp": 328341, "payload": [16, -27, 16, 30, 13, 11, 23, 21, 14, 16, 28, 9, 13, 30, 7], "label": 2}
{"timestamp": 328348, "payload": [16, -26, 16, 30, 13, 11, 22, 21, 14, 16, 28, 10, 13, 29, 6], "label": 2}
{"timestamp": 328348, "payload": [16, -26, 16, 30, 13, 11, 23, 21, 14, 16, 28, 9, 13, 30, 7], "label": 2}
{"timestamp": 328357, "payload": [16, -26, 16, 30, 13, 10, 23, 21, 14, 16, 28, 10, 13, 30, 7], "label": 2}
{"timestamp": 328364, "payload": [17, -26, 15, 30, 13, 10, 22, 21, 14, 16, 28, 10, 12, 29, 7], "label": 2}
{"timestamp": 328364, "payload": [17, -26, 15, 30, 13, 10, 23, 21, 14, 16, 28, 10, 13, 30, 7], "label": 2}
{"timestamp": 328373, "payload": [17, -26, 15, 30, 13, 10, 23, 21, 14, 16, 28, 10, 13, 29, 7], "label": 2}
{"timestamp": 328373, "payload": [17, -25, 15, 30, 13, 10, 23, 21, 14, 16, 28, 10, 13, 29, 7], "label": 2}
{"timestamp": 328380, "payload": [17, -26, 15, 30, 13, 10, 22, 21, 14, 15, 28, 9, 13, 29, 7], "label": 2}
{"timestamp": 328388, "payload": [17, -25, 15, 30, 13, 10, 22, 21, 14, 15, 28, 10, 13, 29, 7], "label": 2}
{"timestamp": 328389, "payload": [17, -25, 15, 30, 13, 10, 23, 21, 14, 15, 28, 10, 12, 29, 8], "label": 2}
{"timestamp": 328396, "payload": [17, -25, 15, 30, 13, 10, 22, 21, 14, 15, 28, 10, 13, 29, 8], "label": 2}
{"timestamp": 328404, "payload": [16, -26, 15, 30, 13, 10, 22, 21, 14, 15, 28, 10, 12, 29, 8], "label": 2}
{"timestamp": 328405, "payload": [16, -25, 16, 30, 13, 10, 22, 21, 14, 15, 28, 10, 12, 29, 8], "label": 2}
{"timestamp": 328412, "payload": [16, -25, 15, 29, 13, 11, 22, 21, 15, 15, 28, 10, 12, 29, 8], "label": 2}
{"timestamp": 328412, "payload": [16, -25, 15, 29, 13, 11, 22, 21, 15, 16, 28, 10, 13, 30, 8], "label": 2}
{"timestamp": 328437, "payload": [16, -26, 15, 29, 13, 11, 22, 21, 15, 15, 28, 10, 13, 30, 8], "label": 2}
{"timestamp": 328444, "payload": [16, -26, 15, 30, 13, 10, 22, 21, 15, 16, 28, 10, 13, 30, 8], "label": 2}
{"timestamp": 328445, "payload": [16, -26, 15, 30, 13, 11, 22, 21, 14, 16, 28, 10, 13, 29, 8], "label": 2}
{"timestamp": 328451, "payload": [16, -26, 15, 30, 13, 10, 23, 20, 14, 16, 28, 10, 13, 29, 7], "label": 2}
{"timestamp": 328453, "payload": [16, -26, 15, 30, 13, 10, 23, 20, 14, 16, 28, 10, 13, 29, 7], "label": 2}
{"timestamp": 328461, "payload": [16, -25, 15, 30, 12, 10, 23, 20, 14, 16, 27, 10, 13, 29, 7], "label": 2}
{"timestamp": 328468, "payload": [16, -26, 15, 30, 12, 10, 23, 20, 14, 16, 27, 10, 13, 29, 8], "label": 2}
{"timestamp": 328469, "payload": [16, -26, 15, 30, 12, 10, 23, 20, 14, 16, 27, 10, 13, 29, 8], "label": 2}
{"timestamp": 328476, "payload": [16, -25, 15, 30, 12, 10, 23, 20, 14, 16, 27, 10, 13, 29, 7], "label": 2}
{"timestamp": 328485, "payload": [16, -26, 15, 30, 12, 10, 23, 20, 14, 16, 27, 10, 13, 29, 7], "label": 2}
{"timestamp": 328485, "payload": [16, -26, 15, 30, 12, 11, 22, 20, 14, 16, 27, 10, 13, 29, 7], "label": 2}
{"timestamp": 328492, "payload": [16, -26, 15, 30, 12, 11, 22, 20, 15, 16, 27, 10, 13, 29, 7], "label": 2}
{"timestamp": 328493, "payload": [16, -26, 15, 30, 12, 11, 22, 20, 15, 16, 27, 10, 13, 28, 8], "label": 2}
{"timestamp": 328501, "payload": [16, -26, 15, 30, 12, 11, 22, 20, 15, 15, 27, 10, 13, 28, 8], "label": 2}
{"timestamp": 328509, "payload": [16, -27, 15, 29, 12, 11, 22, 20, 15, 15, 27, 10, 13, 29, 8], "label": 2}
{"timestamp": 328509, "payload": [16, -27, 15, 29, 12, 11, 22, 20, 15, 15, 27, 10, 13, 28, 8], "label": 2}
{"timestamp": 328517, "payload": [16, -27, 15, 30, 12, 12, 22, 20, 15, 16, 27, 10, 13, 29, 8], "label": 2}
{"timestamp": 328525, "payload": [16, -27, 15, 29, 12, 12, 22, 20, 15, 16, 27, 10, 13, 28, 8], "label": 2}
{"timestamp": 328541, "payload": [15, -27, 15, 30, 12, 12, 22, 20, 16, 16, 27, 10, 13, 29, 8], "label": 2}
{"timestamp": 328549, "payload": [15, -27, 15, 29, 12, 12, 22, 20, 16, 16, 27, 10, 13, 29, 8], "label": 2}
{"timestamp": 328549, "payload": [15, -27, 15, 30, 12, 12, 22, 20, 16, 16, 27, 11, 13, 29, 8], "label": 2}
{"timestamp": 328557, "payload": [15, -28, 16, 30, 12, 12, 22, 20, 16, 16, 27, 10, 14, 29, 8], "label": 2}
{"timestamp": 328565, "payload": [15, -28, 15, 30, 11, 12, 22, 20, 16, 16, 27, 10, 13, 29, 7], "label": 2}
{"timestamp": 328565, "payload": [15, -28, 16, 29, 12, 12, 22, 20, 16, 16, 27, 10, 14, 29, 8], "label": 2}
{"timestamp": 328573, "payload": [15, -27, 15, 29, 12, 12, 22, 20, 16, 16, 27, 10, 13, 29, 8], "label": 2}
{"timestamp": 328573, "payload": [15, -27, 16, 30, 11, 12, 22, 20, 16, 16, 27, 10, 13, 28, 8], "label": 2}
{"timestamp": 328581, "payload": [15, -27, 16, 30, 12, 12, 22, 20, 16, 16, 27, 10, 13, 29, 8], "label": 2}
{"timestamp": 328589, "payload": [15, -27, 16, 29, 12, 12, 22, 20, 16, 16, 27, 10, 13, 29, 8], "label": 2}
{"timestamp": 328589, "payload": [15, -27, 16, 29, 12, 12, 22, 20, 16, 16, 27, 11, 13, 29, 8], "label": 2}
{"timestamp": 328597, "payload": [15, -27, 16, 30, 12, 13, 22, 20, 16, 15, 27, 11, 13, 29, 8], "label": 2}
{"timestamp": 328605, "payload": [15, -27, 16, 29, 12, 12, 22, 21, 16, 15, 28, 10, 13, 29, 8], "label": 2}
{"timestamp": 328605, "payload": [15, -28, 16, 29, 12, 13, 22, 21, 16, 15, 27, 10, 13, 29, 8], "label": 2}
{"timestamp": 328613, "payload": [15, -28, 15, 30, 12, 12, 22, 20, 16, 16, 27, 11, 13, 29, 8], "label": 2}
{"timestamp": 328613, "payload": [16, -28, 15, 30, 12, 13, 22, 21, 16, 15, 28, 11, 13, 29, 8], "label": 2}
{"timestamp": 328621, "payload": [16, -28, 15, 29, 12, 13, 21, 21, 16, 15, 28, 11, 13, 29, 8], "label": 2}
{"timestamp": 328629, "payload": [16, -28, 15, 29, 12, 13, 22, 21, 16, 15, 28, 11, 13, 29, 8], "label": 2}
{"timestamp": 328629, "payload": [16, -28, 15, 29, 12, 13, 22, 21, 17, 15, 28, 11, 13, 29, 8], "label": 2}
{"timestamp": 328637, "payload": [16, -27, 15, 29, 13, 13, 22, 21, 17, 15, 28, 11, 13, 29, 9], "label": 2}
{"timestamp": 328645, "payload": [17, -27, 15, 29, 12, 12, 22, 21, 16, 15, 28, 11, 13, 29, 9], "label": 2}
{"timestamp": 328645, "payload": [16, -27, 15, 29, 13, 12, 22, 21, 16, 15, 28, 11, 13, 30, 9], "label": 2}
{"timestamp": 328653, "payload": [17, -27, 15, 30, 13, 12, 22, 21, 16, 15, 28, 11, 13, 29, 9], "label": 2}
{"timestamp": 328653, "payload": [17, -26, 15, 30, 13, 11, 22, 21, 16, 15, 28, 11, 13, 29, 9], "label": 2}
{"timestamp": 328661, "payload": [17, -26, 14, 30, 13, 11, 22, 21, 15, 15, 28, 10, 13, 29, 9], "label": 2}
{"timestamp": 328669, "payload": [17, -26, 14, 30, 13, 11, 22, 21, 15, 15, 28, 11, 13, 30, 9], "label": 2}
{"timestamp": 328669, "payload": [17, -26, 14, 30, 12, 11, 22, 21, 15, 15, 28, 10, 13, 30, 9], "label": 2}
{"timestamp": 328677, "payload": [17, -25, 14, 29, 12, 11, 22, 20, 15, 15, 28, 10, 13, 29, 9], "label": 2}
{"timestamp": 328685, "payload": [17, -26, 14, 30, 12, 11, 22, 20, 15, 16, 28, 10, 13, 30, 8], "label": 2}
{"timestamp": 328685, "payload": [17, -26, 14, 30, 12, 10, 22, 21, 15, 16, 28, 10, 13, 29, 7], "label": 2}
{"timestamp": 328693, "payload": [17, -25, 15, 30, 12, 10, 22, 20, 14, 16, 28, 10, 13, 29, 8], "label": 2}
{"timestamp": 328693, "payload": [17, -26, 15, 30, 12, 10, 23, 20, 14, 16, 28, 10, 13, 29, 7], "label": 2}
{"timestamp": 328701, "payload": [17, -26, 15, 30, 12, 10, 23, 20, 14, 16, 27, 10, 13, 29, 7], "label": 2}
{"timestamp": 328709, "payload": [17, -25, 15, 30, 11, 10, 23, 20, 14, 16, 27, 10, 14, 29, 7], "label": 2}
{"timestamp": 328709, "payload": [18, -25, 15, 30, 11, 10, 23, 20, 14, 17, 27, 10, 14, 28, 7], "label": 2}
{"timestamp": 328717, "payload": [18, -25, 14, 31, 11, 10, 23, 20, 14, 17, 27, 9, 14, 29, 7], "label": 2}
{"timestamp": 328725, "payload": [18, -25, 14, 30, 11, 10, 23, 20, 14, 17, 27, 9, 14, 28, 6], "label": 2}
{"timestamp": 328725, "payload": [19, -25, 14, 30, 11, 9, 23, 20, 13, 17, 27, 9, 14, 29, 7], "label": 2}
{"timestamp": 328733, "payload": [19, -25, 13, 30, 11, 9, 23, 20, 13, 17, 27, 9, 13, 29, 6], "label": 2}
{"timestamp": 328733, "payload": [19, -25, 13, 31, 11, 9, 23, 20, 13, 17, 27, 9, 14, 29, 6], "label": 2}
{"timestamp": 328741, "payload": [19, -25, 13, 30, 11, 9, 24, 19, 13, 17, 26, 10, 14, 28, 7], "label": 2}
{"timestamp": 328749, "payload": [20, -25, 13, 30, 10, 9, 23, 19, 13, 17, 26, 9, 14, 28, 7], "label": 2}
{"timestamp": 328749, "payload": [20, -25, 12, 31, 10, 9, 23, 18, 13, 17, 26, 9, 14, 28, 7], "label": 2}
{"timestamp": 328757, "payload": [20, -25, 12, 31, 10, 8, 24, 18, 13, 17, 26, 9, 14, 28, 6], "label": 2}
{"timestamp": 328765, "payload": [20, -25, 12, 31, 10, 8, 24, 18, 12, 17, 26, 9, 14, 28, 6], "label": 2}
{"timestamp": 328765, "payload": [20, -24, 12, 31, 10, 8, 24, 18, 12, 17, 26, 9, 15, 28, 6], "label": 2}
{"timestamp": 328773, "payload": [20, -24, 12, 30, 9, 7, 24, 18, 12, 18, 25, 9, 14, 27, 6], "label": 2}
{"timestamp": 328773, "payload": [21, -24, 12, 31, 9, 7, 24, 18, 12, 18, 25, 8, 14, 27, 6], "label": 2}
{"timestamp": 328781, "payload": [21, -24, 12, 30, 9, 7, 24, 18, 12, 18, 25, 9, 14, 27, 6], "label": 2}
{"timestamp": 328789, "payload": [21, -24, 12, 30, 9, 7, 24, 18, 12, 17, 25, 9, 14, 27, 6], "label": 2}
{"timestamp": 328789, "payload": [21, -24, 12, 30, 9, 7, 24, 18, 13, 17, 25, 9, 14, 27, 6], "label": 2}
{"timestamp": 328797, "payload": [21, -23, 12, 30, 10, 8, 24, 18, 13, 17, 25, 9, 14, 27, 6], "label": 2}
{"timestamp": 328805, "payload": [21, -23, 13, 30, 10, 8, 23, 18, 13, 17, 25, 10, 14, 27, 6], "label": 2}
{"timestamp": 328805, "payload": [21, -23, 13, 29, 10, 8, 23, 19, 14, 17, 26, 10, 14, 28, 7], "label": 2}
{"timestamp": 328813, "payload": [22, -23, 13, 29, 11, 8, 23, 19, 14, 16, 27, 11, 14, 28, 8], "label": 2}
{"timestamp": 328813, "payload": [22, -23, 13, 29, 11, 8, 23, 20, 14, 16, 27, 10, 14, 28, 8], "label": 2}
{"timestamp": 328821, "payload": [22, -23, 13, 29, 12, 8, 22, 19, 14, 16, 27, 10, 14, 28, 8], "label": 2}
{"timestamp": 328829, "payload": [22, -24, 12, 29, 12, 8, 23, 20, 14, 16, 27, 10, 14, 29, 7], "label": 2}
{"timestamp": 328829, "payload": [22, -24, 12, 29, 12, 9, 23, 19, 13, 16, 27, 10, 14, 28, 6], "label": 2}
{"timestamp": 328836, "payload": [22, -24, 12, 30, 11, 8, 23, 20, 12, 17, 27, 8, 14, 28, 6], "label": 2}
{"timestamp": 328845, "payload": [22, -24, 11, 30, 11, 8, 23, 19, 11, 17, 27, 7, 14, 28, 5], "label": 2}
{"timestamp": 328845, "payload": [22, -24, 11, 30, 10, 8, 24, 19, 10, 18, 26, 6, 15, 28, 4], "label": 2}
{"timestamp": 328852, "payload": [22, -23, 11, 30, 10, 6, 24, 19, 9, 18, 26, 5, 15, 28, 3], "label": 2}
{"timestamp": 328852, "payload": [22, -23, 11, 30, 10, 5, 25, 18, 8, 19, 26, 4, 15, 28, 2], "label": 2}
{"timestamp": 328861, "payload": [22, -22, 11, 30, 10, 5, 25, 18, 7, 19, 25, 3, 15, 28, 1], "label": 2}
{"timestamp": 328869, "payload": [22, -21, 12, 31, 9, 4, 26, 18, 7, 19, 25, 3, 15, 27, 0], "label": 2}
{"timestamp": 328869, "payload": [22, -21, 13, 31, 9, 3, 26, 17, 7, 19, 25, 3, 14, 27, 0], "label": 2}
{"timestamp": 328877, "payload": [22, -21, 13, 31, 9, 2, 26, 17, 6, 20, 25, 3, 14, 27, 0], "label": 2}
{"timestamp": 328885, "payload": [22, -20, 13, 31, 9, 2, 26, 17, 6, 20, 25, 2, 14, 27, -1], "label": 2}
{"timestamp": 328885, "payload": [23, -20, 13, 31, 8, 2, 26, 17, 6, 20, 24, 2, 14, 27, -1], "label": 2}
{"timestamp": 328893, "payload": [23, -20, 13, 32, 9, 1, 26, 17, 5, 20, 24, 2, 14, 27, -1], "label": 2}
{"timestamp": 328893, "payload": [24, -20, 13, 32, 8, 1, 27, 16, 5, 20, 24, 1, 14, 27, -2], "label": 2}
{"timestamp": 328901, "payload": [24, -20, 13, 32, 9, 0, 27, 16, 4, 21, 24, 1, 15, 27, -2], "label": 2}
{"timestamp": 328909, "payload": [23, -20, 13, 32, 9, 0, 27, 16, 4, 20, 24, 0, 14, 26, -3], "label": 2}
{"timestamp": 328910, "payload": [23, -19, 13, 32, 9, -1, 27, 16, 3, 21, 24, 0, 15, 27, -3], "label": 2}
{"timestamp": 328916, "payload": [23, -18, 13, 32, 9, -1, 28, 17, 3, 21, 24, -1, 15, 27, -4], "label": 2}
{"timestamp": 328924, "payload": [23, -18, 14, 32, 9, -1, 28, 17, 2, 21, 24, -2, 15, 27, -5], "label": 2}
{"timestamp": 328924, "payload": [23, -18, 14, 32, 9, -2, 28, 17, 2, 21, 24, -2, 15, 27, -5], "label": 2}
{"timestamp": 328933, "payload": [23, -17, 14, 32, 9, -3, 29, 17, 1, 22, 24, -3, 15, 28, -6], "label": 2}
{"timestamp": 328933, "payload": [23, -17, 14, 33, 9, -3, 29, 17, 0, 22, 25, -4, 15, 28, -6], "label": 2}
{"timestamp": 328942, "payload": [23, -16, 14, 33, 9, -4, 29, 17, -1, 23, 25, -4, 15, 28, -7], "label": 2}
{"timestamp": 328949, "payload": [24, -16, 14, 33, 9, -4, 30, 17, -1, 23, 25, -5, 15, 28, -7], "label": 2}
{"timestamp": 328949, "payload": [24, -15, 13, 33, 9, -5, 30, 17, -1, 23, 25, -5, 15, 28, -8], "label": 2}
{"timestamp": 328957, "payload": [25, -15, 13, 33, 9, -5, 30, 18, -2, 23, 25, -6, 15, 28, -8], "label": 2}
{"timestamp": 328974, "payload": [26, -14, 14, 33, 10, -6, 29, 17, -2, 22, 25, -6, 14, 28, -8], "label": 2}
{"timestamp": 328981, "payload": [26, -14, 14, 33, 10, -6, 29, 18, -2, 22, 25, -5, 14, 28, -8], "label": 2}
{"timestamp": 328989, "payload": [26, -14, 14, 32, 10, -6, 29, 18, -2, 22, 25, -6, 14, 28, -8], "label": 2}
{"timestamp": 328990, "payload": [26, -14, 14, 32, 10, -6, 29, 18, -2, 22, 25, -6, 14, 28, -8], "label": 2}
{"timestamp": 328997, "payload": [26, -14, 15, 32, 10, -6, 29, 18, -2, 22, 25, -5, 14, 28, -8], "label": 2}
{"timestamp": 329005, "payload": [26, -14, 15, 32, 11, -6, 29, 18, -2, 22, 26, -6, 14, 29, -8], "label": 2}
{"timestamp": 329022, "payload": [27, -13, 14, 32, 12, -6, 29, 19, -3, 22, 26, -6, 14, 29, -8], "label": 2}
{"timestamp": 329029, "payload": [27, -13, 14, 32, 12, -6, 29, 19, -3, 22, 26, -6, 14, 29, -8], "label": 2}
{"timestamp": 329029, "payload": [27, -13, 14, 32, 12, -7, 29, 19, -3, 22, 26, -7, 14, 29, -8], "label": 2}
{"timestamp": 329037, "payload": [27, -13, 14, 32, 12, -7, 29, 19, -3, 22, 26, -6, 14, 29, -8], "label": 2}
{"timestamp": 329045, "payload": [27, -12, 14, 32, 12, -7, 28, 19, -3, 21, 26, -6, 13, 29, -8], "label": 2}
{"timestamp": 329045, "payload": [27, -12, 14, 32, 12, -6, 28, 19, -3, 21, 26, -6, 13, 29, -8], "label": 2}
{"timestamp": 329053, "payload": [27, -12, 15, 32, 12, -6, 28, 19, -2, 21, 26, -6, 13, 29, -7], "label": 2}
{"timestamp": 329053, "payload": [27, -13, 14, 31, 12, -6, 28, 19, -2, 21, 26, -5, 13, 29, -7], "label": 2}
{"timestamp": 329062, "payload": [27, -13, 14, 31, 12, -6, 28, 19, -2, 21, 26, -5, 13, 29, -7], "label": 2}
{"timestamp": 329069, "payload": [28, -13, 15, 31, 12, -6, 28, 19, -2, 20, 26, -5, 13, 29, -7], "label": 2}
{"timestamp": 329069, "payload": [27, -13, 15, 31, 12, -6, 28, 19, -2, 21, 26, -6, 13, 29, -7], "label": 2}
{"timestamp": 329077, "payload": [27, -13, 14, 31, 12, -6, 28, 19, -2, 20, 26, -5, 13, 29, -8], "label": 2}
{"timestamp": 329085, "payload": [27, -13, 14, 31, 12, -5, 28, 19, -1, 20, 26, -5, 13, 29, -8], "label": 2}
{"timestamp": 329085, "payload": [28, -12, 14, 31, 12, -6, 28, 19, -2, 20, 26, -5, 13, 29, -7], "label": 2}
{"timestamp": 329093, "payload": [27, -13, 14, 31, 12, -5, 28, 19, -1, 20, 26, -5, 13, 29, -7], "label": 2}
{"timestamp": 329094, "payload": [27, -13, 15, 31, 12, -6, 28, 19, -2, 20, 26, -5, 13, 29, -8], "label": 2}
{"timestamp": 329102, "payload": [27, -13, 14, 31, 12, -6, 28, 19, -2, 21, 26, -6, 13, 29, -7], "label": 2}
{"timestamp": 329109, "payload": [28, -13, 13, 31, 12, -6, 28, 19, -2, 20, 26, -6, 13, 29, -8], "label": 2}
{"timestamp": 329109, "payload": [28, -12, 14, 31, 12, -6, 28, 19, -2, 20, 26, -6, 13, 29, -8], "label": 2}
{"timestamp": 329118, "payload": [28, -12, 14, 31, 12, -6, 28, 19, -2, 21, 26, -6, 13, 29, -8], "label": 2}
{"timestamp": 329126, "payload": [27, -13, 14, 32, 12, -6, 28, 19, -2, 21, 26, -6, 13, 29, -8], "label": 2}
{"timestamp": 329126, "payload": [27, -13, 14, 31, 11, -6, 28, 19, -2, 21, 26, -6, 13, 29, -8], "label": 2}
{"timestamp": 329134, "payload": [27, -13, 15, 31, 11, -6, 28, 18, -2, 21, 25, -6, 13, 28, -9], "label": 2}
{"timestamp": 329134, "payload": [27, -13, 15, 31, 11, -6, 28, 18, -2, 21, 25, -6, 13, 28, -8], "label": 2}
{"timestamp": 329142, "payload": [27, -13, 15, 31, 12, -5, 27, 18, -1, 20, 25, -5, 13, 28, -8], "label": 2}
{"timestamp": 329150, "payload": [27, -14, 15, 31, 11, -5, 27, 18, -1, 20, 25, -5, 13, 28, -8], "label": 2}
{"timestamp": 329150, "payload": [27, -14, 15, 31, 11, -5, 27, 18, -1, 20, 25, -5, 13, 28, -8], "label": 2}
{"timestamp": 329174, "payload": [27, -14, 13, 32, 11, -6, 29, 18, -3, 22, 26, -6, 14, 29, -8], "label": 2}
{"timestamp": 329174, "payload": [27, -14, 12, 32, 11, -7, 29, 18, -3, 22, 25, -7, 14, 29, -8], "label": 2}
{"timestamp": 329182, "payload": [27, -14, 12, 33, 10, -7, 29, 18, -3, 22, 25, -7, 15, 28, -8], "label": 2}
{"timestamp": 329190, "payload": [27, -14, 12, 33, 10, -7, 30, 18, -3, 22, 25, -7, 14, 29, -9], "label": 2}
{"timestamp": 329190, "payload": [27, -14, 12, 33, 10, -7, 30, 18, -4, 23, 25, -7, 15, 29, -8], "label": 2}
{"timestamp": 329198, "payload": [27, -15, 11, 33, 10, -7, 30, 17, -4, 23, 25, -8, 15, 28, -9], "label": 2}
{"timestamp": 329206, "payload": [27, -14, 11, 33, 10, -8, 30, 17, -5, 23, 25, -9, 15, 28, -10], "label": 2}
{"timestamp": 329206, "payload": [27, -14, 11, 34, 10, -8, 31, 17, -6, 23, 25, -9, 15, 29, -10], "label": 2}
{"timestamp": 329214, "payload": [27, -14, 12, 34, 10, -8, 31, 18, -5, 24, 25, -9, 15, 29, -11], "label": 2}
{"timestamp": 329214, "payload": [26, -14, 12, 34, 10, -8, 31, 18, -5, 24, 25, -10, 15, 29, -11], "label": 2}
{"timestamp": 329221, "payload": [25, -13, 14, 33, 9, -8, 30, 17, -5, 24, 25, -9, 15, 28, -11], "label": 2}
{"timestamp": 329230, "payload": [25, -12, 15, 32, 10, -7, 30, 17, -3, 23, 25, -8, 15, 28, -11], "label": 2}
{"timestamp": 329231, "payload": [24, -12, 16, 31, 10, -6, 28, 18, -2, 22, 25, -7, 14, 28, -10], "label": 2}
{"timestamp": 329238, "payload": [24, -12, 17, 29, 11, -5, 26, 18, -1, 20, 25, -5, 14, 27, -9], "label": 2}
{"timestamp": 329246, "payload": [25, -13, 17, 28, 11, -3, 25, 18, 1, 19, 24, -3, 13, 27, -8], "label": 2}
{"timestamp": 329246, "payload": [24, -14, 18, 27, 12, -1, 25, 19, 3, 18, 25, 0, 12, 27, -6], "label": 2}
{"timestamp": 329254, "payload": [25, -14, 17, 27, 12, -1, 24, 19, 5, 17, 26, 1, 12, 28, -3], "label": 2}
{"timestamp": 329254, "payload": [26, -15, 16, 27, 12, 0, 23, 19, 5, 17, 26, 2, 12, 28, -2], "label": 2}
{"timestamp": 329262, "payload": [26, -16, 15, 27, 12, 1, 23, 20, 6, 16, 26, 3, 12, 28, 0], "label": 2}
{"timestamp": 329270, "payload": [27, -16, 14, 28, 13, 1, 23, 20, 7, 16, 27, 4, 12, 28, 1], "label": 2}
{"timestamp": 329270, "payload": [28, -16, 14, 27, 13, 1, 23, 20, 7, 16, 27, 4, 12, 29, 2], "label": 2}
{"timestamp": 329278, "payload": [28, -17, 13, 28, 13, 1, 23, 20, 7, 17, 27, 4, 13, 28, 1], "label": 2}
{"timestamp": 329286, "payload": [27, -16, 13, 29, 13, 1, 24, 20, 6, 17, 27, 4, 13, 29, 1], "label": 2}
{"timestamp": 329286, "payload": [27, -16, 12, 29, 13, 0, 24, 20, 5, 17, 27, 3, 13, 29, 0], "label": 2}
{"timestamp": 329326, "payload": [28, -15, 11, 33, 11, -5, 28, 19, 3, 20, 26, 0, 14, 29, -3], "label": 2}
{"timestamp": 329326, "payload": [27, -16, 11, 33, 11, -4, 28, 19, 1, 21, 26, -1, 14, 29, -3], "label": 2}
{"timestamp": 329334, "payload": [27, -17, 11, 33, 9, -3, 29, 18, 0, 21, 25, -1, 14, 28, -3], "label": 2}
{"timestamp": 329350, "payload": [24, -21, 12, 33, 8, 0, 29, 16, -1, 23, 23, -5, 16, 27, -6], "label": 2}
{"timestamp": 329358, "payload": [23, -23, 12, 33, 7, 2, 29, 17, -2, 23, 25, -5, 16, 28, -5], "label": 2}
{"timestamp": 329366, "payload": [22, -27, 11, 33, 10, 2, 29, 18, 2, 23, 25, -6, 17, 29, -4], "label": 2}
