{"timestamp": 850372, "payload": [12, -21, 25, 26, 14, 18, 22, 21, 15, 12, 30, 4, 5, 30, -10], "label": 3}
{"timestamp": 850380, "payload": [12, -21, 25, 26, 14, 18, 22, 21, 15, 13, 31, 5, 5, 31, -10], "label": 3}
{"timestamp": 850387, "payload": [12, -21, 25, 26, 14, 18, 22, 21, 15, 12, 31, 5, 4, 31, -10], "label": 3}
{"timestamp": 850388, "payload": [11, -21, 25, 26, 14, 18, 22, 21, 15, 12, 31, 4, 5, 31, -10], "label": 3}
{"timestamp": 850396, "payload": [12, -21, 25, 26, 14, 18, 22, 21, 15, 12, 31, 4, 4, 30, -11], "label": 3}
{"timestamp": 850403, "payload": [12, -21, 25, 26, 14, 18, 22, 22, 15, 12, 31, 4, 5, 31, -10], "label": 3}
{"timestamp": 850404, "payload": [12, -20, 25, 26, 14, 18, 22, 22, 15, 12, 31, 4, 5, 31, -10], "label": 3}
{"timestamp": 850412, "payload": [11, -20, 25, 26, 14, 18, 22, 22, 14, 12, 31, 4, 5, 31, -10], "label": 3}
{"timestamp": 850412, "payload": [11, -20, 25, 26, 14, 17, 22, 22, 14, 12, 31, 4, 5, 31, -10], "label": 3}
{"timestamp": 850436, "payload": [11, -20, 26, 26, 14, 18, 22, 22, 14, 12, 31, 3, 5, 30, -11], "label": 3}
{"timestamp": 850444, "payload": [11, -20, 26, 26, 14, 18, 22, 22, 14, 13, 31, 2, 5, 30, -11], "label": 3}
{"timestamp": 850444, "payload": [11, -21, 26, 26, 14, 18, 22, 22, 14, 12, 31, 3, 5, 30, -12], "label": 3}
{"timestamp": 850451, "payload": [11, -20, 26, 26, 14, 18, 22, 22, 14, 13, 31, 3, 5, 30, -11], "label": 3}
{"timestamp": 850452, "payload": [10, -20, 26, 26, 14, 18, 22, 22, 14, 12, 31, 3, 5, 31, -11], "label": 3}
{"timestamp": 850460, "payload": [10, -20, 27, 26, 14, 18, 22, 22, 14, 13, 31, 3, 5, 30, -11], "label": 3}
{"timestamp": 850468, "payload": [11, -20, 27, 25, 15, 18, 22, 22, 14, 12, 31, 2, 5, 31, -12], "label": 3}
{"timestamp": 850468, "payload": [11, -20, 27, 26, 15, 18, 22, 22, 14, 12, 32, 3, 5, 31, -11], "label": 3}
{"timestamp": 850476, "payload": [10, -20, 26, 26, 15, 18, 22, 23, 14, 12, 32, 3, 5, 31, -12], "label": 3}
{"timestamp": 850484, "payload": [11, -20, 26, 26, 15, 18, 22, 23, 15, 12, 32, 3, 5, 32, -11], "label": 3}
{"timestamp": 850484, "payload": [11, -20, 26, 26, 15, 18, 22, 23, 15, 12, 32, 3, 5, 32, -11], "label": 3}
{"timestamp": 850492, "payload": [11, -20, 25, 26, 15, 18, 22, 23, 14, 13, 32, 3, 5, 32, -11], "label": 3}
{"timestamp": 850492, "payload": [12, -20, 26, 26, 15, 17, 22, 23, 14, 12, 32, 3, 5, 32, -11], "label": 3}
{"timestamp": 850500, "payload": [12, -20, 25, 26, 15, 17, 22, 23, 14, 12, 32, 3, 5, 32, -11], "label": 3}
{"timestamp": 850508, "payload": [12, -19, 25, 26, 15, 17, 22, 23, 14, 13, 32, 3, 5, 31, -11], "label": 3}
{"timestamp": 850508, "payload": [12, -20, 25, 26, 15, 17, 22, 22, 14, 12, 32, 4, 5, 31, -11], "label": 3}
{"timestamp": 850516, "payload": [12, -20, 25, 26, 15, 17, 22, 22, 14, 12, 32, 3, 5, 31, -11], "label": 3}
{"timestamp": 850524, "payload": [12, -20, 25, 26, 15, 17, 22, 22, 14, 12, 31, 4, 5, 31, -11], "label": 3}
{"timestamp": 850524, "payload": [12, -20, 25, 26, 15, 17, 22, 22, 14, 13, 32, 3, 5, 31, -10], "label": 3}
{"timestamp": 850532, "payload": [12, -20, 25, 26, 14, 17, 22, 22, 14, 13, 31, 3, 5, 31, -11], "label": 3}
{"timestamp": 850532, "payload": [12, -20, 25, 26, 14, 17, 22, 21, 14, 13, 31, 3, 5, 31, -11], "label": 3}
{"timestamp": 850540, "payload": [12, -20, 25, 26, 14, 17, 22, 22, 14, 13, 31, 3, 6, 31, -11], "label": 3}
{"timestamp": 850548, "payload": [12, -20, 25, 26, 14, 18, 23, 22, 14, 13, 31, 3, 6, 31, -11], "label": 3}
{"timestamp": 850548, "payload": [12, -20, 25, 27, 14, 18, 23, 21, 14, 13, 31, 3, 6, 30, -12], "label": 3}
{"timestamp": 850556, "payload": [12, -21, 25, 26, 14, 17, 23, 21, 14, 13, 31, 2, 6, 30, -12], "label": 3}
{"timestamp": 850564, "payload": [12, -21, 25, 27, 14, 18, 23, 21, 14, 14, 31, 2, 6, 30, -12], "label": 3}
{"timestamp": 850564, "payload": [12, -21, 25, 27, 14, 18, 23, 21, 14, 14, 31, 3, 6, 30, -12], "label": 3}
{"timestamp": 850572, "payload": [13, -21, 25, 27, 13, 17, 23, 21, 14, 14, 31, 3, 6, 30, -12], "label": 3}
{"timestamp": 850572, "payload": [13, -21, 25, 27, 13, 17, 23, 21, 13, 14, 31, 3, 7, 30, -12], "label": 3}
{"timestamp": 850580, "payload": [13, -21, 25, 27, 13, 17, 23, 21, 14, 14, 30, 3, 7, 30, -12], "label": 3}
{"timestamp": 850588, "payload": [13, -20, 24, 27, 13, 17, 23, 20, 13, 14, 30, 2, 7, 30, -11], "label": 3}
{"timestamp": 850588, "payload": [14, -20, 24, 27, 13, 16, 24, 20, 13, 14, 30, 2, 7, 29, -11], "label": 3}
{"timestamp": 850596, "payload": [14, -20, 23, 27, 12, 16, 24, 20, 13, 14, 30, 3, 7, 29, -12], "label": 3}
{"timestamp": 850660, "payload": [14, -20, 25, 28, 12, 15, 25, 19, 11, 17, 28, 1, 9, 28, -12], "label": 3}
{"timestamp": 850668, "payload": [14, -19, 25, 28, 12, 14, 25, 19, 11, 16, 28, 2, 9, 28, -12], "label": 3}
{"timestamp": 850668, "payload": [14, -18, 25, 29, 12, 13, 25, 19, 11, 16, 28, 2, 9, 28, -12], "label": 3}
{"timestamp": 850676, "payload": [15, -17, 24, 29, 11, 13, 25, 19, 11, 17, 28, 1, 9, 28, -12], "label": 3}
{"timestamp": 850684, "payload": [15, -17, 23, 29, 11, 13, 26, 19, 10, 16, 28, 1, 9, 28, -12], "label": 3}
{"timestamp": 850684, "payload": [16, -17, 22, 29, 11, 13, 26, 19, 10, 17, 28, 1, 9, 28, -12], "label": 3}
{"timestamp": 850692, "payload": [16, -17, 22, 29, 11, 13, 26, 18, 10, 17, 28, 1, 9, 27, -13], "label": 3}
{"timestamp": 850692, "payload": [16, -18, 22, 29, 11, 13, 25, 18, 11, 17, 28, 1, 10, 27, -13], "label": 3}
{"timestamp": 850700, "payload": [16, -18, 23, 29, 10, 14, 25, 18, 10, 16, 27, 1, 9, 27, -13], "label": 3}
{"timestamp": 850708, "payload": [16, -19, 22, 28, 10, 14, 25, 18, 11, 16, 27, 2, 10, 27, -12], "label": 3}
{"timestamp": 850708, "payload": [17, -19, 22, 28, 10, 14, 25, 17, 11, 17, 27, 2, 9, 27, -12], "label": 3}
{"timestamp": 850716, "payload": [17, -19, 21, 29, 10, 14, 25, 17, 11, 17, 27, 1, 9, 26, -13], "label": 3}
{"timestamp": 850724, "payload": [18, -20, 20, 29, 10, 15, 25, 18, 11, 17, 27, 1, 9, 27, -14], "label": 3}
{"timestamp": 850724, "payload": [18, -20, 20, 28, 10, 14, 25, 18, 10, 17, 27, 1, 9, 27, -14], "label": 3}
{"timestamp": 850732, "payload": [18, -21, 20, 29, 10, 14, 26, 18, 10, 18, 28, 1, 11, 27, -13], "label": 3}
{"timestamp": 850732, "payload": [18, -20, 19, 29, 9, 14, 26, 17, 11, 18, 27, 1, 11, 27, -13], "label": 3}
{"timestamp": 850740, "payload": [19, -20, 19, 29, 9, 14, 26, 17, 11, 18, 28, 2, 11, 27, -14], "label": 3}
{"timestamp": 850748, "payload": [20, -23, 16, 29, 10, 14, 26, 18, 11, 18, 28, 1, 8, 27, -15], "label": 3}
{"timestamp": 850748, "payload": [23, -26, 12, 29, 9, 14, 27, 18, 11, 18, 28, -1, 8, 27, -17], "label": 3}
{"timestamp": 850756, "payload": [25, -28, 10, 31, 9, 15, 29, 18, 8, 21, 27, -3, 9, 27, -18], "label": 3}
{"timestamp": 850764, "payload": [25, -29, 12, 32, 8, 14, 30, 18, 6, 23, 27, -7, 13, 26, -18], "label": 3}
{"timestamp": 850764, "payload": [21, -28, 16, 33, 8, 13, 30, 16, 6, 23, 27, -6, 15, 24, -19], "label": 3}
{"timestamp": 850772, "payload": [18, -27, 19, 32, 14, 11, 27, 20, 5, 21, 29, -3, 12, 29, -15], "label": 3}
{"timestamp": 850772, "payload": [16, -24, 20, 33, 9, 11, 32, 14, 4, 23, 16, -6, 10, 14, -17], "label": 3}
{"timestamp": 850780, "payload": [15, -24, 21, 32, 10, 11, 30, 19, -4, 26, 22, -16, 12, 19, -22], "label": 3}
{"timestamp": 850788, "payload": [11, -24, 25, 34, 11, 6, 33, 18, -7, 28, 22, -17, 11, 19, -24], "label": 3}
{"timestamp": 850788, "payload": [8, -18, 30, 35, 11, 4, 30, 17, -3, 26, 20, -13, 14, 13, -28], "label": 3}
{"timestamp": 850828, "payload": [21, -17, 27, 26, 10, 18, 15, 17, 18, 3, 26, 12, -2, 27, 2], "label": 3}
{"timestamp": 850828, "payload": [22, -17, 24, 21, 7, 17, 14, 15, 17, 2, 24, 18, 1, 28, 6], "label": 3}
{"timestamp": 850836, "payload": [24, -21, 19, 23, 9, 19, 15, 17, 19, 4, 25, 13, 2, 27, 1], "label": 3}
{"timestamp": 850844, "payload": [23, -13, 21, 22, 10, 18, 15, 18, 19, 4, 28, 13, 1, 32, 1], "label": 3}
{"timestamp": 850844, "payload": [22, -10, 21, 23, 12, 17, 15, 21, 19, 6, 30, 13, 3, 34, 0], "label": 3}
{"timestamp": 850852, "payload": [22, -13, 19, 25, 15, 15, 19, 23, 17, 7, 32, 12, 4, 34, 0], "label": 3}
{"timestamp": 850852, "payload": [22, -13, 19, 26, 17, 15, 19, 25, 17, 7, 34, 12, 6, 37, -1], "label": 3}
{"timestamp": 850860, "payload": [21, -12, 19, 25, 18, 16, 19, 26, 17, 8, 35, 11, 6, 38, -3], "label": 3}
{"timestamp": 850867, "payload": [19, -12, 21, 23, 19, 18, 18, 26, 17, 11, 35, 10, 7, 37, -4], "label": 3}
{"timestamp": 850867, "payload": [17, -15, 23, 23, 19, 19, 19, 27, 19, 12, 35, 10, 9, 37, -7], "label": 3}
{"timestamp": 850875, "payload": [16, -17, 25, 22, 17, 21, 18, 26, 20, 11, 36, 11, 10, 37, -8], "label": 3}
{"timestamp": 850884, "payload": [15, -18, 27, 20, 18, 23, 17, 27, 21, 12, 37, 11, 11, 37, -9], "label": 3}
{"timestamp": 850884, "payload": [14, -19, 27, 20, 17, 24, 18, 27, 21, 12, 37, 10, 11, 37, -10], "label": 3}
{"timestamp": 850892, "payload": [14, -20, 28, 21, 18, 24, 19, 27, 21, 13, 37, 11, 13, 37, -10], "label": 3}
{"timestamp": 850892, "payload": [13, -19, 27, 23, 18, 23, 19, 27, 20, 13, 37, 10, 12, 37, -11], "label": 3}
{"timestamp": 850900, "payload": [13, -18, 27, 23, 17, 22, 20, 26, 19, 14, 36, 9, 12, 35, -11], "label": 3}
{"timestamp": 850908, "payload": [14, -18, 25, 24, 17, 20, 22, 26, 18, 15, 35, 9, 12, 35, -11], "label": 3}
{"timestamp": 850908, "payload": [14, -16, 25, 26, 15, 19, 23, 24, 17, 16, 32, 8, 12, 33, -10], "label": 3}
{"timestamp": 850916, "payload": [15, -16, 24, 27, 14, 18, 23, 22, 16, 16, 31, 8, 12, 31, -10], "label": 3}
{"timestamp": 850924, "payload": [15, -17, 23, 28, 12, 17, 24, 20, 15, 17, 29, 8, 12, 29, -9], "label": 3}
{"timestamp": 850924, "payload": [15, -16, 23, 28, 10, 17, 24, 18, 14, 16, 26, 8, 11, 27, -8], "label": 3}
{"timestamp": 850932, "payload": [16, -17, 22, 28, 9, 16, 24, 16, 14, 16, 25, 8, 10, 26, -8], "label": 3}
{"timestamp": 850932, "payload": [16, -16, 22, 29, 7, 16, 24, 14, 14, 16, 23, 8, 10, 24, -8], "label": 3}
{"timestamp": 850940, "payload": [15, -17, 23, 29, 6, 16, 24, 14, 14, 16, 22, 8, 10, 23, -8], "label": 3}
{"timestamp": 850948, "payload": [15, -16, 23, 29, 5, 16, 24, 13, 14, 16, 21, 8, 10, 22, -9], "label": 3}
{"timestamp": 850948, "payload": [15, -17, 24, 29, 5, 17, 24, 13, 14, 16, 21, 8, 10, 22, -9], "label": 3}
{"timestamp": 850956, "payload": [14, -18, 24, 28, 5, 17, 24, 13, 14, 17, 22, 7, 10, 22, -10], "label": 3}
{"timestamp": 850964, "payload": [14, -18, 25, 28, 6, 18, 23, 13, 14, 17, 22, 8, 11, 22, -10], "label": 3}
{"timestamp": 850964, "payload": [13, -18, 25, 27, 6, 18, 23, 14, 14, 16, 23, 8, 11, 23, -10], "label": 3}
{"timestamp": 850972, "payload": [13, -18, 25, 27, 7, 18, 23, 15, 15, 16, 24, 7, 11, 24, -10], "label": 3}
{"timestamp": 850972, "payload": [13, -18, 25, 27, 8, 18, 23, 16, 14, 16, 25, 7, 11, 25, -10], "label": 3}
{"timestamp": 850980, "payload": [14, -17, 25, 28, 8, 17, 24, 17, 14, 17, 25, 8, 11, 26, -10], "label": 3}
{"timestamp": 850987, "payload": [14, -16, 24, 28, 9, 17, 24, 18, 14, 16, 26, 8, 11, 27, -9], "label": 3}
{"timestamp": 851004, "payload": [15, -17, 24, 26, 10, 18, 21, 18, 17, 13, 27, 10, 9, 28, -6], "label": 3}
{"timestamp": 851012, "payload": [15, -17, 24, 25, 10, 20, 19, 18, 18, 12, 27, 10, 9, 28, -6], "label": 3}
{"timestamp": 851012, "payload": [15, -18, 25, 23, 10, 21, 19, 18, 19, 11, 28, 11, 8, 29, -5], "label": 3}
{"timestamp": 851020, "payload": [14, -19, 25, 23, 10, 22, 18, 18, 20, 10, 28, 12, 8, 29, -5], "label": 3}
{"timestamp": 851028, "payload": [14, -19, 26, 22, 10, 24, 17, 19, 21, 9, 28, 12, 8, 30, -5], "label": 3}
{"timestamp": 851028, "payload": [13, -20, 27, 21, 10, 25, 16, 19, 22, 8, 30, 13, 8, 31, -5], "label": 3}
{"timestamp": 851036, "payload": [12, -21, 27, 20, 11, 25, 16, 20, 23, 8, 31, 13, 7, 32, -4], "label": 3}
{"timestamp": 851044, "payload": [8, -26, 33, 20, 12, 25, 16, 21, 21, 5, 32, 12, 6, 33, 0], "label": 3}
{"timestamp": 851044, "payload": [6, -28, 34, 20, 14, 23, 16, 21, 20, 7, 29, 13, 6, 33, -1], "label": 3}
{"timestamp": 851052, "payload": [13, -21, 28, 20, 13, 25, 16, 21, 24, 7, 30, 16, 7, 31, -7], "label": 3}
{"timestamp": 851052, "payload": [17, -4, 23, 20, 11, 29, 14, 21, 29, 6, 34, 16, 7, 33, -12], "label": 3}
{"timestamp": 851060, "payload": [15, -5, 25, 20, 12, 27, 15, 22, 28, 5, 35, 14, 5, 36, -7], "label": 3}
{"timestamp": 851068, "payload": [11, -11, 29, 22, 15, 23, 16, 23, 24, 6, 32, 15, 5, 36, -3], "label": 3}
{"timestamp": 851068, "payload": [10, -16, 31, 22, 16, 20, 17, 24, 20, 6, 34, 14, 6, 37, -2], "label": 3}
{"timestamp": 851076, "payload": [11, -19, 29, 23, 17, 19, 18, 24, 18, 6, 33, 11, 4, 34, -3], "label": 3}
{"timestamp": 851084, "payload": [12, -20, 26, 23, 18, 19, 18, 26, 17, 7, 33, 10, 5, 36, -4], "label": 3}
{"timestamp": 851084, "payload": [15, -19, 23, 25, 18, 19, 19, 26, 17, 7, 35, 9, 2, 36, -6], "label": 3}
{"timestamp": 851092, "payload": [16, -19, 22, 24, 18, 19, 19, 26, 16, 9, 33, 7, 3, 35, -6], "label": 3}
{"timestamp": 851093, "payload": [16, -20, 21, 25, 19, 19, 20, 25, 15, 10, 33, 6, 3, 35, -8], "label": 3}
{"timestamp": 851100, "payload": [16, -21, 21, 25, 18, 19, 20, 25, 15, 10, 34, 5, 4, 34, -8], "label": 3}
{"timestamp": 851108, "payload": [16, -21, 22, 25, 19, 17, 21, 25, 14, 12, 34, 4, 4, 35, -9], "label": 3}
{"timestamp": 851109, "payload": [16, -21, 22, 26, 17, 18, 22, 25, 13, 9, 34, 4, 5, 34, -10], "label": 3}
{"timestamp": 851116, "payload": [16, -22, 22, 26, 16, 18, 20, 24, 14, 11, 32, 3, 3, 32, -9], "label": 3}
{"timestamp": 851124, "payload": [16, -22, 21, 26, 16, 18, 21, 23, 15, 10, 32, 3, 3, 32, -10], "label": 3}
{"timestamp": 851125, "payload": [16, -21, 21, 25, 16, 18, 21, 24, 15, 11, 33, 3, 4, 31, -13], "label": 3}
{"timestamp": 851133, "payload": [16, -21, 21, 26, 14, 18, 21, 23, 15, 12, 33, 2, 6, 32, -13], "label": 3}
{"timestamp": 851133, "payload": [16, -21, 21, 26, 14, 18, 22, 23, 14, 12, 34, 3, 4, 33, -12], "label": 3}
{"timestamp": 851140, "payload": [16, -21, 21, 27, 14, 18, 22, 23, 14, 12, 33, 3, 3, 32, -13], "label": 3}
{"timestamp": 851148, "payload": [15, -22, 22, 27, 14, 18, 22, 23, 14, 13, 33, 2, 3, 32, -13], "label": 3}
{"timestamp": 851149, "payload": [15, -21, 22, 26, 15, 18, 23, 23, 13, 12, 32, 1, 4, 31, -13], "label": 3}
{"timestamp": 851156, "payload": [14, -21, 23, 27, 14, 17, 24, 23, 13, 14, 32, 1, 4, 31, -14], "label": 3}
{"timestamp": 851164, "payload": [14, -21, 23, 28, 14, 17, 24, 23, 13, 14, 33, 0, 5, 30, -15], "label": 3}
{"timestamp": 851165, "payload": [13, -21, 24, 28, 14, 16, 24, 23, 11, 14, 33, -1, 6, 30, -16], "label": 3}
{"timestamp": 851188, "payload": [11, -20, 27, 28, 13, 16, 24, 21, 10, 15, 29, -1, 6, 26, -17], "label": 3}
{"timestamp": 851188, "payload": [11, -20, 28, 28, 13, 16, 24, 20, 11, 15, 28, -1, 6, 25, -17], "label": 3}
{"timestamp": 851196, "payload": [11, -21, 29, 28, 12, 16, 24, 19, 11, 16, 28, -1, 6, 25, -17], "label": 3}
{"timestamp": 851204, "payload": [11, -21, 29, 29, 11, 16, 24, 19, 11, 16, 28, -1, 6, 25, -17], "label": 3}
{"timestamp": 851204, "payload": [11, -22, 29, 28, 11, 17, 25, 19, 11, 15, 28, -1, 6, 25, -17], "label": 3}
{"timestamp": 851212, "payload": [11, -22, 28, 28, 11, 17, 25, 19, 11, 15, 28, -1, 6, 25, -17], "label": 3}
{"timestamp": 851213, "payload": [11, -22, 28, 28, 11, 17, 25, 19, 11, 15, 27, -1, 6, 24, -17], "label": 3}
{"timestamp": 851219, "payload": [12, -22, 28, 28, 11, 17, 25, 19, 11, 15, 28, -2, 5, 25, -16], "label": 3}
{"timestamp": 851227, "payload": [12, -21, 28, 28, 11, 17, 25, 19, 10, 15, 28, -2, 6, 25, -17], "label": 3}
{"timestamp": 851229, "payload": [12, -21, 27, 28, 12, 16, 25, 19, 11, 15, 28, -1, 6, 25, -17], "label": 3}
{"timestamp": 851236, "payload": [13, -21, 27, 28, 12, 15, 25, 19, 10, 16, 28, -2, 6, 26, -17], "label": 3}
{"timestamp": 851244, "payload": [13, -20, 26, 29, 12, 14, 25, 20, 9, 16, 28, -2, 6, 26, -16], "label": 3}
{"timestamp": 851245, "payload": [13, -18, 26, 29, 13, 13, 25, 20, 9, 16, 29, -2, 6, 26, -17], "label": 3}
{"timestamp": 851252, "payload": [14, -18, 25, 29, 13, 13, 25, 21, 8, 16, 29, -2, 6, 26, -16], "label": 3}
{"timestamp": 851253, "payload": [14, -17, 24, 29, 13, 12, 25, 21, 8, 16, 29, -2, 6, 26, -17], "label": 3}
{"timestamp": 851261, "payload": [14, -16, 24, 29, 14, 11, 25, 21, 8, 15, 29, -2, 6, 27, -16], "label": 3}
{"timestamp": 851268, "payload": [15, -16, 24, 28, 14, 12, 24, 21, 8, 15, 29, -2, 6, 26, -16], "label": 3}
{"timestamp": 851269, "payload": [15, -15, 24, 29, 13, 11, 24, 21, 8, 15, 29, -2, 6, 27, -16], "label": 3}
{"timestamp": 851276, "payload": [15, -16, 24, 28, 14, 11, 24, 21, 8, 15, 29, -2, 6, 26, -15], "label": 3}
{"timestamp": 851284, "payload": [15, -16, 24, 28, 14, 12, 24, 21, 8, 14, 29, -1, 6, 26, -16], "label": 3}
{"timestamp": 851285, "payload": [15, -17, 24, 28, 14, 12, 24, 21, 8, 14, 29, -1, 6, 27, -15], "label": 3}
{"timestamp": 851293, "payload": [16, -16, 23, 28, 14, 12, 24, 21, 9, 14, 29, -1, 5, 27, -15], "label": 3}
{"timestamp": 851293, "payload": [16, -16, 23, 28, 14, 12, 23, 21, 9, 14, 29, -1, 6, 27, -15], "label": 3}
{"timestamp": 851301, "payload": [16, -16, 23, 28, 14, 12, 23, 21, 9, 14, 29, -1, 6, 27, -15], "label": 3}
{"timestamp": 851309, "payload": [16, -16, 24, 28, 14, 12, 23, 21, 9, 15, 30, -1, 6, 27, -15], "label": 3}
{"timestamp": 851309, "payload": [16, -15, 23, 28, 14, 12, 23, 21, 9, 14, 30, 0, 6, 28, -15], "label": 3}
{"timestamp": 851317, "payload": [16, -15, 23, 28, 14, 12, 24, 22, 9, 14, 30, 0, 6, 28, -14], "label": 3}
{"timestamp": 851325, "payload": [16, -15, 22, 28, 15, 11, 23, 22, 9, 14, 30, 0, 6, 28, -14], "label": 3}
{"timestamp": 851325, "payload": [17, -15, 22, 28, 15, 11, 23, 22, 9, 14, 30, 0, 5, 28, -14], "label": 3}
{"timestamp": 851333, "payload": [17, -15, 22, 28, 15, 11, 23, 22, 9, 14, 30, 0, 6, 28, -14], "label": 3}
{"timestamp": 851350, "payload": [17, -15, 23, 28, 15, 12, 23, 22, 10, 14, 30, 0, 6, 28, -14], "label": 3}
{"timestamp": 851357, "payload": [17, -15, 23, 28, 15, 12, 23, 22, 10, 14, 30, 1, 6, 28, -14], "label": 3}
{"timestamp": 851365, "payload": [17, -16, 23, 27, 15, 13, 23, 22, 10, 13, 30, 1, 6, 28, -14], "label": 3}
{"timestamp": 851365, "payload": [16, -16, 24, 27, 14, 13, 23, 21, 10, 14, 30, 1, 5, 28, -14], "label": 3}
{"timestamp": 851373, "payload": [16, -17, 24, 27, 14, 14, 23, 21, 11, 14, 29, 1, 6, 29, -13], "label": 3}
{"timestamp": 851373, "payload": [16, -17, 24, 27, 14, 14, 23, 21, 11, 14, 30, 1, 6, 29, -13], "label": 3}
{"timestamp": 851397, "payload": [15, -18, 25, 28, 14, 15, 23, 21, 11, 14, 30, 1, 6, 28, -14], "label": 3}
{"timestamp": 851404, "payload": [15, -18, 25, 28, 14, 14, 24, 21, 11, 14, 30, 1, 6, 28, -14], "label": 3}
{"timestamp": 851404, "payload": [15, -18, 25, 28, 14, 14, 24, 21, 11, 14, 30, 1, 6, 28, -14], "label": 3}
{"timestamp": 851413, "payload": [15, -18, 25, 28, 14, 14, 24, 21, 11, 14, 30, 1, 6, 28, -14], "label": 3}
{"timestamp": 851413, "payload": [15, -17, 24, 28, 14, 14, 23, 21, 11, 14, 30, 0, 6, 28, -14], "label": 3}
{"timestamp": 851421, "payload": [15, -17, 25, 28, 14, 15, 23, 21, 11, 14, 30, 0, 6, 28, -14], "label": 3}
{"timestamp": 851429, "payload": [15, -18, 25, 27, 14, 14, 23, 21, 11, 14, 30, 1, 6, 28, -14], "label": 3}
{"timestamp": 851429, "payload": [15, -18, 25, 27, 13, 15, 23, 21, 11, 14, 30, 1, 6, 28, -14], "label": 3}
{"timestamp": 851437, "payload": [14, -18, 25, 28, 14, 14, 23, 21, 11, 14, 30, 1, 6, 28, -14], "label": 3}
{"timestamp": 851445, "payload": [14, -18, 25, 27, 14, 15, 23, 21, 11, 14, 30, 1, 6, 28, -14], "label": 3}
{"timestamp": 851445, "payload": [14, -18, 25, 27, 14, 15, 23, 21, 11, 14, 30, 1, 6, 28, -14], "label": 3}
{"timestamp": 851453, "payload": [14, -18, 25, 28, 14, 14, 24, 21, 11, 14, 30, 1, 5, 28, -14], "label": 3}
{"timestamp": 851453, "payload": [14, -18, 25, 28, 14, 14, 23, 21, 11, 13, 30, 1, 6, 28, -13], "label": 3}
{"timestamp": 851461, "payload": [14, -18, 25, 27, 14, 15, 23, 21, 11, 13, 30, 1, 6, 28, -13], "label": 3}
{"timestamp": 851469, "payload": [14, -18, 25, 27, 14, 15, 23, 21, 12, 13, 30, 2, 6, 28, -13], "label": 3}
{"timestamp": 851469, "payload": [14, -18, 24, 27, 14, 15, 23, 21, 12, 13, 30, 2, 6, 29, -13], "label": 3}
{"timestamp": 851477, "payload": [15, -18, 24, 27, 14, 15, 23, 21, 12, 13, 30, 2, 6, 29, -13], "label": 3}
{"timestamp": 851485, "payload": [15, -19, 24, 27, 14, 15, 23, 21, 12, 14, 31, 2, 6, 29, -13], "label": 3}
{"timestamp": 851485, "payload": [15, -19, 24, 28, 14, 15, 23, 21, 12, 13, 30, 2, 6, 29, -13], "label": 3}
{"timestamp": 851493, "payload": [15, -19, 24, 28, 14, 15, 24, 21, 12, 14, 30, 2, 6, 29, -13], "label": 3}
{"timestamp": 851493, "payload": [15, -18, 24, 28, 14, 15, 24, 21, 12, 14, 30, 2, 6, 29, -13], "label": 3}
{"timestamp": 851502, "payload": [14, -18, 24, 28, 14, 15, 24, 21, 11, 14, 30, 2, 6, 29, -13], "label": 3}
{"timestamp": 851509, "payload": [14, -18, 24, 28, 13, 14, 24, 21, 11, 14, 30, 1, 6, 29, -13], "label": 3}
{"timestamp": 851509, "payload": [14, -18, 24, 28, 13, 15, 24, 21, 11, 14, 30, 1, 6, 29, -13], "label": 3}
{"timestamp": 851517, "payload": [14, -18, 24, 27, 13, 15, 24, 21, 11, 14, 30, 1, 6, 28, -13], "label": 3}
{"timestamp": 851525, "payload": [14, -18, 24, 28, 13, 15, 23, 21, 12, 14, 30, 1, 6, 28, -13], "label": 3}
{"timestamp": 851525, "payload": [14, -19, 25, 27, 13, 15, 23, 20, 12, 14, 29, 2, 6, 28, -13], "label": 3}
{"timestamp": 851534, "payload": [14, -19, 25, 27, 12, 16, 23, 20, 12, 13, 29, 2, 6, 28, -13], "label": 3}
{"timestamp": 851550, "payload": [14, -19, 25, 27, 13, 16, 23, 20, 13, 14, 30, 3, 6, 29, -12], "label": 3}
{"timestamp": 851557, "payload": [14, -19, 24, 27, 13, 16, 23, 21, 13, 13, 30, 2, 6, 29, -12], "label": 3}
{"timestamp": 851565, "payload": [14, -19, 24, 27, 13, 15, 23, 21, 13, 14, 31, 2, 6, 29, -12], "label": 3}
