{"timestamp": 312117, "payload": [16, -37, 17, 23, 7, 23, 24, 15, 18, 18, 28, 6, 12, 32, -3], "label": 1}
{"timestamp": 312124, "payload": [15, -35, 18, 25, 7, 22, 25, 15, 17, 19, 28, 6, 12, 32, -4], "label": 1}
{"timestamp": 312124, "payload": [15, -32, 19, 26, 7, 21, 25, 15, 17, 19, 28, 6, 12, 32, -3], "label": 1}
{"timestamp": 312133, "payload": [15, -29, 19, 26, 7, 21, 26, 15, 17, 20, 28, 7, 11, 31, -3], "label": 1}
{"timestamp": 312140, "payload": [15, -26, 19, 28, 7, 20, 26, 15, 16, 19, 27, 7, 11, 31, -3], "label": 1}
{"timestamp": 312140, "payload": [15, -23, 19, 28, 7, 19, 27, 15, 16, 19, 27, 7, 11, 31, -3], "label": 1}
{"timestamp": 312148, "payload": [15, -21, 18, 28, 7, 19, 27, 14, 16, 19, 27, 7, 10, 31, -3], "label": 1}
{"timestamp": 312155, "payload": [16, -20, 18, 28, 7, 18, 26, 14, 16, 19, 26, 6, 10, 30, -3], "label": 1}
{"timestamp": 312155, "payload": [16, -19, 18, 28, 7, 19, 26, 14, 16, 19, 26, 6, 10, 30, -3], "label": 1}
{"timestamp": 312164, "payload": [16, -20, 17, 28, 7, 19, 25, 14, 16, 18, 26, 7, 9, 30, -3], "label": 1}
{"timestamp": 312164, "payload": [16, -21, 18, 27, 7, 20, 24, 14, 17, 17, 26, 8, 9, 30, -2], "label": 1}
{"timestamp": 312172, "payload": [15, -22, 18, 25, 7, 21, 23, 14, 18, 16, 26, 9, 8, 31, -2], "label": 1}
{"timestamp": 312180, "payload": [15, -23, 19, 23, 7, 22, 22, 15, 20, 15, 27, 9, 8, 31, -1], "label": 1}
{"timestamp": 312181, "payload": [15, -24, 20, 22, 7, 24, 21, 15, 21, 15, 27, 10, 8, 31, -1], "label": 1}
{"timestamp": 312188, "payload": [14, -24, 20, 21, 8, 25, 20, 15, 22, 14, 27, 10, 7, 32, -1], "label": 1}
{"timestamp": 312211, "payload": [14, -24, 22, 21, 9, 26, 20, 16, 23, 14, 29, 12, 7, 33, -1], "label": 1}
{"timestamp": 312220, "payload": [14, -24, 21, 22, 9, 26, 20, 17, 23, 14, 29, 11, 7, 33, -1], "label": 1}
{"timestamp": 312221, "payload": [15, -24, 21, 22, 9, 25, 21, 17, 22, 14, 30, 10, 7, 33, -1], "label": 1}
{"timestamp": 312228, "payload": [15, -23, 21, 23, 9, 24, 22, 17, 21, 15, 30, 10, 7, 33, -2], "label": 1}
{"timestamp": 312235, "payload": [15, -23, 20, 25, 9, 23, 23, 17, 20, 15, 30, 10, 7, 33, -2], "label": 1}
{"timestamp": 312237, "payload": [15, -22, 20, 25, 10, 22, 23, 17, 19, 16, 29, 9, 8, 33, -2], "label": 1}
{"timestamp": 312244, "payload": [15, -22, 20, 26, 10, 22, 23, 17, 19, 16, 29, 9, 8, 33, -2], "label": 1}
{"timestamp": 312244, "payload": [15, -21, 20, 26, 9, 21, 24, 17, 18, 16, 29, 8, 8, 33, -3], "label": 1}
{"timestamp": 312253, "payload": [15, -21, 20, 26, 9, 21, 25, 17, 18, 17, 29, 7, 8, 32, -3], "label": 1}
{"timestamp": 312260, "payload": [15, -21, 20, 26, 9, 20, 24, 17, 18, 17, 29, 7, 8, 32, -3], "label": 1}
{"timestamp": 312260, "payload": [15, -21, 20, 26, 9, 21, 24, 16, 17, 17, 28, 7, 8, 31, -3], "label": 1}
{"timestamp": 312269, "payload": [15, -21, 21, 26, 9, 21, 24, 16, 18, 17, 28, 7, 8, 31, -3], "label": 1}
{"timestamp": 312276, "payload": [15, -22, 21, 25, 9, 21, 24, 16, 18, 16, 28, 7, 8, 31, -3], "label": 1}
{"timestamp": 312276, "payload": [14, -22, 21, 25, 9, 22, 23, 16, 18, 16, 28, 7, 8, 31, -4], "label": 1}
{"timestamp": 312285, "payload": [14, -22, 22, 24, 9, 22, 23, 16, 19, 16, 28, 8, 8, 31, -3], "label": 1}
{"timestamp": 312285, "payload": [14, -22, 22, 23, 9, 23, 22, 16, 20, 15, 28, 8, 7, 31, -3], "label": 1}
{"timestamp": 312291, "payload": [14, -22, 22, 23, 9, 23, 21, 16, 20, 15, 28, 9, 8, 31, -3], "label": 1}
{"timestamp": 312301, "payload": [14, -22, 22, 22, 9, 24, 21, 16, 20, 14, 28, 9, 8, 31, -3], "label": 1}
{"timestamp": 312301, "payload": [13, -23, 22, 22, 9, 24, 20, 16, 21, 14, 29, 9, 8, 31, -3], "label": 1}
{"timestamp": 312308, "payload": [14, -22, 22, 22, 9, 24, 21, 16, 21, 14, 28, 9, 8, 31, -3], "label": 1}
{"timestamp": 312316, "payload": [14, -22, 22, 22, 9, 24, 21, 16, 21, 14, 28, 9, 7, 31, -3], "label": 1}
{"timestamp": 312317, "payload": [14, -22, 22, 22, 9, 24, 21, 16, 21, 14, 28, 9, 7, 31, -3], "label": 1}
{"timestamp": 312324, "payload": [14, -22, 21, 23, 10, 23, 21, 16, 20, 14, 29, 10, 7, 32, -3], "label": 1}
{"timestamp": 312325, "payload": [15, -22, 21, 23, 9, 23, 21, 17, 20, 15, 28, 9, 7, 32, -3], "label": 1}
{"timestamp": 312333, "payload": [15, -22, 21, 24, 9, 22, 22, 16, 20, 15, 29, 9, 7, 31, -2], "label": 1}
{"timestamp": 312340, "payload": [15, -21, 20, 24, 9, 22, 22, 16, 19, 15, 28, 9, 7, 31, -2], "label": 1}
{"timestamp": 312341, "payload": [15, -21, 20, 25, 9, 22, 22, 16, 19, 15, 28, 8, 7, 31, -2], "label": 1}
{"timestamp": 312349, "payload": [15, -21, 20, 25, 9, 21, 23, 16, 19, 15, 28, 8, 7, 31, -3], "label": 1}
{"timestamp": 312356, "payload": [15, -21, 20, 25, 9, 21, 23, 16, 18, 15, 28, 8, 7, 31, -3], "label": 1}
{"timestamp": 312357, "payload": [15, -21, 20, 25, 9, 21, 23, 16, 18, 15, 28, 8, 7, 31, -2], "label": 1}
{"timestamp": 312365, "payload": [15, -21, 20, 25, 9, 21, 23, 16, 18, 15, 28, 8, 7, 31, -3], "label": 1}
{"timestamp": 312365, "payload": [15, -21, 20, 25, 8, 21, 23, 15, 18, 16, 27, 8, 7, 31, -3], "label": 1}
{"timestamp": 312373, "payload": [15, -21, 20, 25, 8, 21, 22, 15, 19, 15, 27, 8, 7, 31, -3], "label": 1}
{"timestamp": 312380, "payload": [15, -21, 20, 25, 8, 21, 22, 15, 19, 15, 27, 8, 7, 30, -2], "label": 1}
{"timestamp": 312381, "payload": [15, -21, 20, 24, 8, 21, 22, 15, 19, 15, 27, 9, 7, 30, -2], "label": 1}
{"timestamp": 312389, "payload": [15, -22, 20, 24, 8, 22, 22, 15, 19, 15, 27, 9, 7, 30, -2], "label": 1}
{"timestamp": 312397, "payload": [15, -22, 20, 24, 8, 22, 22, 14, 19, 15, 26, 9, 7, 30, -2], "label": 1}
{"timestamp": 312397, "payload": [15, -22, 20, 23, 8, 23, 21, 14, 19, 15, 26, 9, 7, 30, -2], "label": 1}
{"timestamp": 312405, "payload": [14, -22, 20, 23, 7, 23, 21, 14, 20, 14, 26, 10, 7, 30, -1], "label": 1}
{"timestamp": 312405, "payload": [15, -23, 20, 23, 7, 23, 21, 14, 20, 15, 27, 10, 7, 30, -1], "label": 1}
{"timestamp": 312413, "payload": [14, -23, 20, 23, 7, 24, 21, 14, 21, 14, 26, 10, 7, 30, -1], "label": 1}
{"timestamp": 312421, "payload": [14, -23, 20, 22, 7, 24, 21, 14, 21, 14, 26, 10, 7, 30, -1], "label": 1}
{"timestamp": 312421, "payload": [14, -23, 20, 22, 7, 24, 21, 14, 22, 15, 27, 10, 7, 31, -1], "label": 1}
{"timestamp": 312429, "payload": [14, -23, 20, 22, 7, 25, 21, 14, 22, 15, 27, 11, 7, 31, -1], "label": 1}
{"timestamp": 312437, "payload": [14, -24, 20, 22, 8, 25, 21, 14, 22, 15, 27, 11, 7, 32, 0], "label": 1}
{"timestamp": 312437, "payload": [13, -24, 21, 21, 7, 26, 21, 15, 22, 14, 28, 11, 7, 32, 0], "label": 1}
{"timestamp": 312445, "payload": [13, -25, 21, 22, 8, 25, 21, 15, 22, 15, 28, 11, 7, 32, 0], "label": 1}
{"timestamp": 312445, "payload": [13, -25, 21, 22, 8, 26, 21, 15, 22, 15, 28, 11, 7, 32, -1], "label": 1}
{"timestamp": 312453, "payload": [13, -24, 21, 22, 8, 25, 21, 15, 22, 15, 28, 11, 8, 32, -1], "label": 1}
{"timestamp": 312461, "payload": [13, -25, 21, 22, 8, 25, 21, 15, 22, 15, 28, 10, 7, 32, -1], "label": 1}
{"timestamp": 312461, "payload": [13, -24, 21, 22, 8, 25, 22, 15, 22, 15, 28, 10, 7, 32, -1], "label": 1}
{"timestamp": 312469, "payload": [13, -24, 21, 23, 8, 25, 22, 15, 22, 15, 28, 10, 7, 32, -1], "label": 1}
{"timestamp": 312477, "payload": [13, -24, 22, 23, 8, 25, 22, 15, 22, 15, 28, 10, 7, 32, -1], "label": 1}
{"timestamp": 312477, "payload": [13, -24, 21, 23, 8, 25, 22, 15, 22, 15, 28, 10, 7, 32, -1], "label": 1}
{"timestamp": 312485, "payload": [13, -24, 21, 23, 8, 25, 22, 15, 22, 15, 28, 10, 7, 32, -1], "label": 1}
{"timestamp": 312485, "payload": [13, -24, 21, 23, 8, 25, 21, 15, 22, 15, 28, 10, 7, 32, -1], "label": 1}
{"timestamp": 312493, "payload": [13, -24, 21, 23, 8, 25, 21, 15, 22, 14, 28, 10, 7, 32, -1], "label": 1}
{"timestamp": 312501, "payload": [13, -23, 21, 23, 8, 25, 21, 15, 22, 14, 28, 10, 6, 32, 0], "label": 1}
{"timestamp": 312501, "payload": [13, -24, 21, 23, 8, 25, 21, 15, 22, 14, 28, 10, 6, 32, 0], "label": 1}
{"timestamp": 312509, "payload": [13, -23, 21, 22, 8, 25, 21, 15, 22, 14, 28, 11, 6, 32, 0], "label": 1}
{"timestamp": 312517, "payload": [13, -23, 21, 22, 8, 25, 21, 15, 22, 14, 28, 11, 6, 32, 0], "label": 1}
{"timestamp": 312533, "payload": [13, -24, 21, 22, 8, 25, 21, 16, 22, 14, 29, 10, 7, 32, 0], "label": 1}
{"timestamp": 312541, "payload": [13, -23, 21, 22, 8, 25, 21, 16, 22, 14, 29, 10, 6, 32, -1], "label": 1}
{"timestamp": 312541, "payload": [13, -24, 21, 22, 8, 25, 21, 16, 22, 14, 28, 10, 7, 33, -1], "label": 1}
{"timestamp": 312549, "payload": [13, -23, 21, 23, 9, 25, 21, 16, 22, 15, 29, 10, 6, 32, -1], "label": 1}
{"timestamp": 312557, "payload": [13, -23, 22, 22, 9, 25, 21, 16, 22, 14, 29, 10, 6, 32, -1], "label": 1}
{"timestamp": 312558, "payload": [13, -23, 22, 22, 9, 25, 21, 16, 22, 14, 29, 10, 7, 32, -1], "label": 1}
{"timestamp": 312565, "payload": [13, -23, 22, 22, 9, 25, 21, 16, 22, 14, 29, 10, 6, 33, -1], "label": 1}
{"timestamp": 312565, "payload": [13, -23, 22, 22, 9, 25, 21, 16, 22, 14, 29, 10, 6, 33, -1], "label": 1}
{"timestamp": 312573, "payload": [12, -24, 22, 23, 9, 25, 21, 16, 22, 14, 29, 10, 6, 33, -1], "label": 1}
{"timestamp": 312581, "payload": [12, -23, 22, 22, 9, 25, 21, 16, 22, 14, 29, 10, 6, 33, -1], "label": 1}
{"timestamp": 312581, "payload": [12, -23, 22, 23, 9, 25, 21, 16, 22, 14, 28, 10, 6, 33, -1], "label": 1}
{"timestamp": 312589, "payload": [12, -24, 22, 23, 9, 25, 21, 16, 22, 14, 29, 10, 6, 32, -1], "label": 1}
{"timestamp": 312597, "payload": [12, -23, 22, 23, 9, 25, 21, 16, 22, 14, 28, 10, 6, 32, -1], "label": 1}
{"timestamp": 312597, "payload": [12, -24, 22, 22, 9, 25, 21, 16, 22, 14, 28, 10, 6, 32, -1], "label": 1}
{"timestamp": 312605, "payload": [12, -23, 22, 23, 9, 25, 21, 16, 22, 14, 29, 10, 6, 32, -1], "label": 1}
{"timestamp": 312606, "payload": [12, -23, 22, 23, 9, 25, 21, 16, 22, 14, 28, 10, 6, 32, -2], "label": 1}
{"timestamp": 312613, "payload": [12, -23, 22, 22, 9, 25, 21, 16, 22, 14, 28, 10, 6, 32, -1], "label": 1}
{"timestamp": 312622, "payload": [12, -23, 22, 22, 9, 25, 21, 16, 22, 14, 28, 10, 6, 32, -1], "label": 1}
{"timestamp": 312622, "payload": [13, -23, 22, 22, 9, 25, 21, 16, 22, 15, 29, 10, 6, 32, -1], "label": 1}
{"timestamp": 312629, "payload": [12, -23, 22, 22, 8, 25, 21, 16, 22, 14, 29, 10, 6, 32, -1], "label": 1}
{"timestamp": 312638, "payload": [12, -23, 22, 22, 9, 25, 21, 16, 22, 14, 28, 10, 6, 32, -1], "label": 1}
{"timestamp": 312638, "payload": [12, -23, 22, 22, 9, 25, 21, 16, 22, 14, 29, 10, 6, 32, -1], "label": 1}
{"timestamp": 312645, "payload": [12, -23, 22, 23, 9, 25, 21, 16, 22, 14, 29, 10, 6, 32, -1], "label": 1}
{"timestamp": 312645, "payload": [12, -23, 22, 22, 9, 25, 21, 16, 22, 14, 29, 10, 7, 32, -1], "label": 1}
{"timestamp": 312654, "payload": [12, -23, 22, 23, 9, 25, 21, 16, 22, 14, 29, 10, 6, 33, -1], "label": 1}
{"timestamp": 312661, "payload": [13, -23, 22, 22, 9, 25, 21, 16, 22, 14, 29, 10, 6, 32, -1], "label": 1}
{"timestamp": 312661, "payload": [13, -23, 22, 22, 9, 25, 21, 16, 22, 14, 29, 10, 6, 33, -1], "label": 1}
{"timestamp": 312670, "payload": [13, -23, 21, 22, 9, 25, 20, 16, 22, 14, 29, 10, 6, 33, -1], "label": 1}
{"timestamp": 312677, "payload": [13, -23, 22, 22, 9, 25, 21, 17, 22, 14, 30, 10, 6, 33, -1], "label": 1}
{"timestamp": 312678, "payload": [12, -23, 22, 23, 9, 25, 21, 16, 22, 14, 30, 10, 6, 33, -2], "label": 1}
{"timestamp": 312686, "payload": [12, -23, 22, 23, 9, 25, 21, 17, 22, 14, 30, 10, 6, 33, -1], "label": 1}
{"timestamp": 312686, "payload": [13, -23, 22, 23, 9, 24, 21, 16, 22, 15, 30, 10, 7, 33, -2], "label": 1}
{"timestamp": 312692, "payload": [12, -24, 22, 24, 10, 24, 22, 17, 21, 14, 30, 10, 7, 33, -2], "label": 1}
{"timestamp": 312718, "payload": [13, -24, 22, 24, 9, 24, 22, 17, 21, 15, 30, 10, 7, 34, -2], "label": 1}
{"timestamp": 312718, "payload": [12, -24, 22, 25, 9, 24, 22, 17, 20, 15, 30, 10, 7, 33, -2], "label": 1}
{"timestamp": 312725, "payload": [13, -24, 22, 24, 9, 23, 22, 17, 20, 15, 30, 9, 7, 34, -2], "label": 1}
{"timestamp": 312726, "payload": [12, -25, 22, 25, 10, 23, 23, 17, 20, 15, 30, 9, 6, 33, -1], "label": 1}
{"timestamp": 312734, "payload": [12, -24, 22, 24, 9, 22, 23, 17, 20, 15, 30, 9, 7, 33, -2], "label": 1}
{"timestamp": 312741, "payload": [12, -23, 21, 24, 9, 22, 23, 17, 20, 15, 30, 8, 8, 33, -2], "label": 1}
{"timestamp": 312742, "payload": [12, -24, 22, 24, 9, 23, 23, 17, 20, 15, 30, 9, 8, 33, -3], "label": 1}
{"timestamp": 312750, "payload": [12, -24, 22, 25, 9, 23, 23, 17, 20, 15, 30, 9, 8, 33, -3], "label": 1}
{"timestamp": 312758, "payload": [13, -24, 22, 24, 9, 23, 22, 17, 20, 15, 29, 8, 8, 33, -3], "label": 1}
{"timestamp": 312758, "payload": [13, -23, 21, 25, 9, 23, 23, 17, 20, 15, 30, 8, 8, 33, -3], "label": 1}
{"timestamp": 312765, "payload": [13, -24, 22, 25, 9, 22, 23, 17, 19, 15, 29, 8, 7, 33, -2], "label": 1}
{"timestamp": 312766, "payload": [13, -24, 22, 26, 9, 21, 23, 17, 19, 16, 29, 8, 7, 33, -3], "label": 1}
{"timestamp": 312774, "payload": [13, -24, 22, 26, 9, 22, 24, 17, 19, 16, 29, 8, 8, 32, -2], "label": 1}
{"timestamp": 312782, "payload": [13, -24, 21, 26, 8, 21, 24, 17, 18, 16, 29, 8, 8, 32, -2], "label": 1}
{"timestamp": 312782, "payload": [14, -24, 21, 26, 8, 21, 24, 17, 18, 16, 29, 8, 8, 32, -3], "label": 1}
{"timestamp": 312790, "payload": [14, -24, 20, 27, 8, 20, 24, 16, 18, 16, 29, 8, 8, 32, -2], "label": 1}
{"timestamp": 312797, "payload": [14, -24, 20, 27, 8, 20, 25, 16, 17, 17, 28, 7, 8, 32, -3], "label": 1}
{"timestamp": 312798, "payload": [14, -23, 20, 27, 7, 20, 25, 16, 17, 17, 28, 7, 8, 31, -3], "label": 1}
{"timestamp": 312806, "payload": [14, -24, 20, 28, 6, 19, 25, 15, 16, 17, 28, 7, 9, 31, -3], "label": 1}
{"timestamp": 312806, "payload": [15, -24, 19, 28, 7, 19, 25, 15, 16, 17, 27, 7, 9, 31, -3], "label": 1}
{"timestamp": 312814, "payload": [15, -24, 19, 28, 6, 19, 25, 15, 16, 18, 27, 6, 9, 30, -3], "label": 1}
{"timestamp": 312822, "payload": [15, -23, 19, 28, 6, 18, 25, 15, 15, 18, 27, 6, 10, 30, -3], "label": 1}
{"timestamp": 312822, "payload": [15, -23, 19, 28, 6, 18, 26, 15, 15, 18, 26, 5, 10, 30, -3], "label": 1}
{"timestamp": 312830, "payload": [15, -23, 18, 28, 6, 18, 26, 14, 15, 18, 26, 5, 10, 30, -3], "label": 1}
{"timestamp": 312838, "payload": [15, -23, 18, 28, 5, 17, 26, 14, 15, 19, 26, 5, 10, 29, -3], "label": 1}
{"timestamp": 312854, "payload": [16, -23, 18, 28, 5, 17, 26, 13, 14, 19, 25, 5, 11, 29, -3], "label": 1}
{"timestamp": 312862, "payload": [16, -23, 17, 28, 4, 17, 26, 13, 14, 19, 25, 6, 11, 29, -3], "label": 1}
{"timestamp": 312862, "payload": [16, -24, 17, 28, 4, 17, 26, 13, 14, 19, 25, 6, 11, 29, -3], "label": 1}
{"timestamp": 312870, "payload": [15, -24, 17, 28, 4, 17, 26, 13, 14, 19, 25, 6, 11, 29, -3], "label": 1}
{"timestamp": 312878, "payload": [15, -24, 17, 28, 4, 17, 26, 13, 15, 19, 25, 5, 11, 29, -3], "label": 1}
{"timestamp": 312878, "payload": [16, -24, 17, 28, 4, 17, 26, 13, 15, 19, 25, 6, 11, 29, -3], "label": 1}
{"timestamp": 312886, "payload": [16, -24, 17, 28, 4, 18, 26, 13, 15, 19, 25, 6, 11, 28, -3], "label": 1}
{"timestamp": 312886, "payload": [16, -24, 17, 28, 4, 18, 26, 13, 15, 19, 25, 6, 11, 28, -3], "label": 1}
{"timestamp": 312894, "payload": [16, -24, 17, 28, 4, 18, 26, 13, 16, 19, 25, 7, 12, 29, -2], "label": 1}
{"timestamp": 312902, "payload": [16, -24, 17, 28, 3, 18, 26, 13, 16, 19, 25, 7, 11, 29, -2], "label": 1}
{"timestamp": 312902, "payload": [16, -24, 17, 28, 4, 19, 26, 12, 16, 19, 25, 7, 11, 29, -2], "label": 1}
{"timestamp": 312910, "payload": [15, -24, 17, 27, 4, 19, 26, 13, 16, 19, 25, 7, 12, 29, -2], "label": 1}
{"timestamp": 312917, "payload": [15, -24, 17, 28, 4, 19, 26, 13, 16, 19, 25, 7, 11, 29, -2], "label": 1}
{"timestamp": 312917, "payload": [15, -24, 17, 28, 4, 19, 26, 13, 16, 19, 26, 7, 12, 29, -2], "label": 1}
{"timestamp": 312926, "payload": [15, -24, 17, 28, 4, 18, 26, 13, 16, 20, 26, 6, 12, 29, -3], "label": 1}
{"timestamp": 312926, "payload": [15, -24, 17, 28, 4, 18, 26, 13, 15, 20, 26, 6, 12, 30, -3], "label": 1}
{"timestamp": 312934, "payload": [15, -24, 17, 28, 4, 18, 26, 13, 15, 20, 25, 6, 12, 30, -3], "label": 1}
{"timestamp": 312942, "payload": [15, -24, 17, 29, 4, 18, 27, 13, 15, 20, 26, 6, 12, 29, -3], "label": 1}
{"timestamp": 312942, "payload": [15, -24, 17, 29, 4, 18, 27, 13, 15, 20, 25, 6, 12, 29, -3], "label": 1}
{"timestamp": 312950, "payload": [15, -24, 17, 29, 4, 18, 27, 13, 15, 20, 25, 6, 12, 29, -3], "label": 1}
{"timestamp": 312958, "payload": [15, -24, 17, 29, 4, 17, 27, 13, 15, 20, 25, 6, 12, 29, -3], "label": 1}
{"timestamp": 312958, "payload": [15, -24, 17, 28, 4, 17, 27, 13, 15, 20, 25, 6, 12, 29, -2], "label": 1}
{"timestamp": 312966, "payload": [16, -24, 17, 28, 3, 18, 27, 12, 15, 20, 25, 6, 12, 29, -2], "label": 1}
{"timestamp": 312966, "payload": [16, -24, 16, 29, 3, 18, 26, 12, 15, 20, 25, 7, 12, 29, -2], "label": 1}
{"timestamp": 312974, "payload": [16, -24, 16, 28, 3, 18, 26, 12, 16, 20, 25, 7, 12, 29, -2], "label": 1}
{"timestamp": 312982, "payload": [16, -24, 16, 28, 3, 18, 26, 12, 15, 19, 25, 7, 11, 29, -2], "label": 1}
{"timestamp": 312982, "payload": [16, -24, 16, 28, 3, 18, 26, 12, 16, 19, 25, 8, 11, 29, -1], "label": 1}
{"timestamp": 312990, "payload": [16, -24, 16, 28, 3, 19, 25, 12, 16, 19, 25, 8, 11, 29, -1], "label": 1}
{"timestamp": 312998, "payload": [16, -24, 16, 27, 3, 19, 25, 12, 17, 18, 25, 8, 11, 29, -1], "label": 1}
{"timestamp": 312998, "payload": [16, -25, 16, 27, 3, 20, 25, 12, 17, 18, 26, 9, 11, 29, -1], "label": 1}
{"timestamp": 313006, "payload": [16, -25, 17, 27, 3, 20, 25, 12, 18, 19, 25, 9, 11, 30, -1], "label": 1}
{"timestamp": 313006, "payload": [16, -25, 17, 27, 3, 20, 25, 13, 18, 19, 26, 8, 11, 30, -1], "label": 1}
{"timestamp": 313014, "payload": [15, -25, 17, 27, 4, 20, 25, 13, 18, 19, 26, 9, 11, 30, -1], "label": 1}
{"timestamp": 313022, "payload": [15, -25, 17, 27, 4, 20, 25, 13, 18, 19, 26, 8, 12, 30, -2], "label": 1}
{"timestamp": 313022, "payload": [15, -25, 17, 28, 4, 20, 26, 13, 17, 19, 26, 8, 12, 30, -2], "label": 1}
{"timestamp": 313030, "payload": [15, -25, 18, 28, 4, 19, 26, 13, 16, 19, 26, 7, 12, 30, -2], "label": 1}
{"timestamp": 313046, "payload": [15, -24, 17, 29, 4, 18, 27, 13, 15, 20, 26, 6, 12, 29, -3], "label": 1}
{"timestamp": 313054, "payload": [16, -24, 17, 29, 4, 18, 27, 13, 15, 20, 25, 6, 12, 29, -3], "label": 1}
{"timestamp": 313062, "payload": [15, -24, 18, 29, 4, 18, 27, 13, 15, 20, 26, 6, 12, 29, -3], "label": 1}
{"timestamp": 313062, "payload": [16, -24, 18, 29, 4, 18, 26, 13, 15, 20, 26, 6, 11, 30, -2], "label": 1}
{"timestamp": 313070, "payload": [16, -24, 17, 28, 4, 18, 27, 13, 16, 19, 26, 6, 11, 29, -3], "label": 1}
{"timestamp": 313078, "payload": [16, -24, 18, 28, 4, 18, 26, 13, 16, 19, 26, 7, 11, 29, -3], "label": 1}
{"timestamp": 313078, "payload": [15, -24, 18, 28, 5, 19, 26, 13, 16, 19, 26, 7, 11, 30, -2], "label": 1}
{"timestamp": 313086, "payload": [16, -24, 18, 27, 5, 19, 25, 14, 17, 18, 26, 7, 11, 30, -2], "label": 1}
{"timestamp": 313086, "payload": [15, -24, 18, 27, 5, 19, 25, 14, 17, 18, 26, 7, 11, 30, -3], "label": 1}
{"timestamp": 313094, "payload": [15, -24, 18, 27, 5, 20, 25, 14, 17, 18, 27, 7, 11, 30, -2], "label": 1}
{"timestamp": 313102, "payload": [15, -24, 18, 27, 6, 19, 25, 15, 17, 18, 27, 7, 11, 31, -3], "label": 1}
{"timestamp": 313102, "payload": [15, -23, 18, 27, 7, 19, 25, 15, 17, 18, 28, 7, 11, 31, -3], "label": 1}
{"timestamp": 313110, "payload": [15, -23, 18, 27, 7, 19, 25, 15, 17, 18, 28, 6, 11, 32, -3], "label": 1}
{"timestamp": 313118, "payload": [15, -23, 18, 28, 7, 19, 26, 16, 16, 19, 28, 6, 11, 32, -3], "label": 1}
{"timestamp": 313118, "payload": [15, -23, 18, 28, 7, 18, 26, 16, 16, 19, 29, 6, 11, 32, -3], "label": 1}
{"timestamp": 313126, "payload": [15, -23, 18, 28, 7, 18, 26, 16, 15, 19, 28, 6, 12, 32, -3], "label": 1}
{"timestamp": 313126, "payload": [15, -23, 18, 28, 7, 18, 26, 16, 15, 19, 28, 5, 12, 32, -4], "label": 1}
{"timestamp": 313134, "payload": [15, -23, 18, 28, 7, 18, 26, 16, 15, 20, 28, 5, 12, 32, -3], "label": 1}
{"timestamp": 313142, "payload": [15, -23, 18, 29, 7, 18, 26, 16, 15, 19, 28, 5, 12, 32, -3], "label": 1}
{"timestamp": 313142, "payload": [15, -23, 18, 29, 7, 18, 27, 16, 15, 19, 28, 5, 11, 32, -4], "label": 1}
{"timestamp": 313150, "payload": [15, -23, 18, 29, 6, 18, 26, 16, 15, 19, 27, 5, 12, 31, -3], "label": 1}
{"timestamp": 313158, "payload": [15, -23, 18, 29, 6, 18, 26, 15, 15, 19, 27, 6, 12, 31, -3], "label": 1}
{"timestamp": 313158, "payload": [15, -24, 18, 28, 6, 18, 26, 15, 15, 19, 27, 5, 11, 31, -3], "label": 1}
{"timestamp": 313166, "payload": [15, -24, 18, 29, 6, 18, 26, 14, 15, 19, 27, 6, 11, 30, -3], "label": 1}
{"timestamp": 313166, "payload": [15, -24, 18, 28, 6, 18, 26, 14, 16, 19, 26, 6, 11, 30, -3], "label": 1}
{"timestamp": 313174, "payload": [16, -24, 18, 28, 5, 19, 26, 14, 16, 19, 26, 6, 11, 30, -3], "label": 1}
{"timestamp": 313182, "payload": [16, -24, 18, 28, 5, 19, 26, 14, 16, 19, 26, 7, 11, 30, -3], "label": 1}
{"timestamp": 313182, "payload": [16, -24, 18, 28, 5, 19, 26, 14, 16, 19, 26, 7, 11, 30, -3], "label": 1}
{"timestamp": 313190, "payload": [16, -24, 18, 28, 5, 19, 25, 13, 16, 19, 26, 7, 11, 30, -2], "label": 1}
{"timestamp": 313198, "payload": [16, -25, 17, 28, 4, 19, 25, 13, 17, 19, 26, 7, 11, 30, -2], "label": 1}
{"timestamp": 313198, "payload": [16, -25, 17, 28, 4, 19, 25, 13, 16, 19, 26, 7, 11, 30, -2], "label": 1}
{"timestamp": 313206, "payload": [16, -24, 17, 28, 4, 19, 26, 13, 16, 19, 26, 7, 12, 30, -2], "label": 1}
{"timestamp": 313206, "payload": [15, -24, 17, 28, 4, 19, 26, 13, 16, 20, 26, 7, 12, 30, -2], "label": 1}
{"timestamp": 313230, "payload": [15, -25, 16, 29, 4, 18, 27, 13, 15, 21, 26, 6, 13, 30, -3], "label": 1}
{"timestamp": 313238, "payload": [15, -25, 16, 29, 3, 18, 28, 13, 15, 21, 26, 6, 13, 30, -3], "label": 1}
{"timestamp": 313238, "payload": [15, -25, 16, 29, 3, 17, 28, 13, 14, 21, 25, 6, 13, 29, -3], "label": 1}
{"timestamp": 313246, "payload": [15, -25, 16, 29, 2, 17, 28, 12, 14, 21, 25, 6, 13, 29, -3], "label": 1}
{"timestamp": 313246, "payload": [16, -25, 16, 29, 2, 17, 28, 12, 14, 21, 24, 6, 13, 29, -2], "label": 1}
{"timestamp": 313253, "payload": [16, -25, 15, 30, 1, 16, 28, 11, 14, 21, 24, 6, 14, 28, -2], "label": 1}
